lambda_networks/__init__.py
lambda_networks/lambda_networks.py
lambda_networks/tfkeras.py
lambda_networks-0.4.0.dist-info/LICENSE
lambda_networks-0.4.0.dist-info/METADATA
lambda_networks-0.4.0.dist-info/WHEEL
lambda_networks-0.4.0.dist-info/top_level.txt
lambda_networks-0.4.0.dist-info/RECORD
