Metadata-Version: 2.1
Name: lambda-networks
Version: 0.4.0
Summary: Lambda Networks - Pytorch
Home-page: https://github.com/lucidrains/lambda-networks
Author: Phil Wang
Author-email: lucidrains@gmail.com
License: MIT
Keywords: artificial intelligence,attention mechanism,image recognition
Platform: UNKNOWN
Classifier: Development Status :: 4 - Beta
Classifier: Intended Audience :: Developers
Classifier: Topic :: Scientific/Engineering :: Artificial Intelligence
Classifier: License :: OSI Approved :: MIT License
Classifier: Programming Language :: Python :: 3.6
Requires-Dist: torch (>=1.6)
Requires-Dist: einops (>=0.3)
